README.md
setup.py
youtube_video_viewer_bot/__init__.py
youtube_video_viewer_bot.egg-info/PKG-INFO
youtube_video_viewer_bot.egg-info/SOURCES.txt
youtube_video_viewer_bot.egg-info/dependency_links.txt
youtube_video_viewer_bot.egg-info/requires.txt
youtube_video_viewer_bot.egg-info/top_level.txt